{
    "Pand ID": "0599100000162479",
    "Archetype ID": "D.1965",
    "Construction Year": 1912,
    "Number of Floors": 3,
    "Wall Area": 255.74,
    "Roof Area (Flat)": 13.28,
    "Roof Area (Sloped)": 144.16,
    "Floor Area": 129.07,
    "Shared Wall Area": 0.0,
    "Absolute Height (70%)": 2.256747007369995,
    "Surfaces": [
        {
            "Type": "G",
            "Centroid": {
                "x": 97761.41185,
                "y": 438311.3574
            },
            "Distances": [
                3.996383819469435,
                3.8512164743916646,
                3.910641000187927,
                3.3095829695618435,
                2.8260276595327554,
                5.646613209006132,
                6.969289514177881,
                8.285457551167143,
                7.321699415585416,
                5.2959100381659745,
                6.7029226336326095,
                6.475751387484741,
                7.45944624835885,
                10.035593073308096,
                8.480906916889591,
                6.386570592485095,
                6.277182658855689,
                5.106681606740063,
                3.903550631483836,
                3.772066931078939
            ],
            "UnitPairs": [
                [
                    -0.7516420183102025,
                    -0.6595712822057713
                ],
                [
                    -0.7386886764026844,
                    -0.6740467634774684
                ],
                [
                    -0.7185139213418135,
                    -0.6955125770523566
                ],
                [
                    -0.6411230718568045,
                    -0.7674380800643754
                ],
                [
                    -0.5381582147241952,
                    -0.84284383839764
                ],
                [
                    -0.11986831308436699,
                    -0.9927898002690742
                ],
                [
                    -0.04603769141043504,
                    -0.9989397033703273
                ],
                [
                    0.778249114207121,
                    -0.627955664227843
                ],
                [
                    0.8379407090828777,
                    -0.5457612738750197
                ],
                [
                    0.9930587872683705,
                    -0.11761906745538053
                ],
                [
                    0.9992879772157698,
                    -0.03772981038933305
                ],
                [
                    0.9290273267165337,
                    0.3700111163383219
                ],
                [
                    0.7071771582437953,
                    0.7070363971241013
                ],
                [
                    0.42839022752189826,
                    0.9035938318535249
                ],
                [
                    -0.6356454625477489,
                    0.771981117607457
                ],
                [
                    -0.7466996459131036,
                    0.6651613629738619
                ],
                [
                    -0.7574815420265114,
                    0.6528565795709947
                ],
                [
                    -0.8486626607560473,
                    0.528934483881006
                ],
                [
                    -0.9870116629038466,
                    0.1606486143475365
                ],
                [
                    -0.9890731177826807,
                    0.14742580398168895
                ]
            ]
        },
        {
            "Type": "F",
            "Centroid": {
                "x": 97761.39051999999,
                "y": 438310.95466
            },
            "Distances": [
                3.72591319490382,
                3.5752225072091717,
                3.7783493083496342,
                3.625613638519985,
                2.9754970569528787,
                2.996604267483486,
                2.4830695793604716,
                1.7346645946971098,
                5.24429027187912,
                6.565995136767047,
                1.6135827391286195,
                8.055787205235406,
                7.128326926845243,
                5.285067592379957,
                6.721150459272797,
                6.654672801586991,
                7.763968880393482,
                1.5049831945649488,
                10.409772223085783,
                1.2209938803984852,
                8.782483763500046,
                6.64599570087572,
                6.531751089553715,
                3.967507521843927,
                3.83143742946148
            ],
            "UnitPairs": [
                [
                    -0.8004802699294938,
                    -0.5993591055899666
                ],
                [
                    -0.7897466505364079,
                    -0.6134331487346644
                ],
                [
                    -0.780901859306195,
                    -0.6246537329850255
                ],
                [
                    -0.7691167007871346,
                    -0.6391083637148817
                ],
                [
                    -0.7301368337489187,
                    -0.6833009615119122
                ],
                [
                    -0.7009667652101014,
                    -0.7131939386105905
                ],
                [
                    -0.6038976968111315,
                    -0.7970618368647509
                ],
                [
                    -0.32889355195115816,
                    -0.9443670004214203
                ],
                [
                    -0.12499689490887304,
                    -0.992157132848996
                ],
                [
                    -0.04561684767457953,
                    -0.9989590097737916
                ],
                [
                    0.6367693301919908,
                    -0.7710543561428361
                ],
                [
                    0.8030847681539832,
                    -0.5958647960393892
                ],
                [
                    0.8636640916145177,
                    -0.5040677899406685
                ],
                [
                    0.9991319709164534,
                    -0.04165698852057334
                ],
                [
                    0.9997514623026789,
                    0.022293802359742064
                ],
                [
                    0.9072542227130682,
                    0.42058266175545844
                ],
                [
                    0.6821871753478864,
                    0.7311775829378743
                ],
                [
                    0.4408554211096599,
                    0.8975781290106306
                ],
                [
                    0.4150407816251608,
                    0.9098028080787484
                ],
                [
                    -0.6032135064845008,
                    0.7975797550055249
                ],
                [
                    -0.6113896870847189,
                    0.7913296724668231
                ],
                [
                    -0.7143429237193647,
                    0.6997958183156497
                ],
                [
                    -0.7246938738318844,
                    0.6890709609543394
                ],
                [
                    -0.9657246971548842,
                    0.2595685059962151
                ],
                [
                    -0.9681797153896909,
                    0.2502559463987559
                ]
            ]
        },
        {
            "Type": "R",
            "Centroid": {
                "x": 97757.078,
                "y": 438314.0585
            },
            "Distances": [
                0.0
            ],
            "UnitPairs": [
                [
                    0.0,
                    0.0
                ]
            ]
        }
    ],
    "Annual Heating [kWh/m2]": 251.2496968611052,
    "Annual Cooling [kWh/m2]": 1.112022993639113
}