{
    "Pand ID": "0599100000016719",
    "Archetype ID": "D.1965-1974",
    "Construction Year": 1965,
    "Number of Floors": 1,
    "Wall Area": 221.52,
    "Roof Area (Flat)": 156.4,
    "Roof Area (Sloped)": 0.0,
    "Floor Area": 157.31,
    "Shared Wall Area": 0.0,
    "Absolute Height (70%)": 1.5477840900421143,
    "Surfaces": [
        {
            "Type": "G",
            "Centroid": {
                "x": 94669.90939814814,
                "y": 432711.7282407408
            },
            "Distances": [
                5.119155610363687,
                7.931960148204482,
                6.572617262668648,
                6.655448448626352,
                6.567002558848333,
                7.206257914211381,
                9.228206802703985,
                9.07501367902348,
                9.192586607342935,
                4.88413220013164,
                5.823609188285905,
                6.327139612941213,
                4.307789771912503,
                5.4595440299652305,
                6.2159063503155005,
                5.341184091246669,
                5.724180350213633,
                8.78567217102487,
                7.507119342979418,
                7.031669951836314,
                8.838912530324697,
                8.501787738824111,
                10.615523263748836,
                7.209664867118211,
                8.542834700389495,
                9.086154023631982,
                6.9122585642786545
            ],
            "UnitPairs": [
                [
                    -0.9999985422933373,
                    -0.001707457525282658
                ],
                [
                    -0.9077388203686192,
                    -0.41953573625590895
                ],
                [
                    -0.5594648221837843,
                    -0.8288540961706509
                ],
                [
                    -0.5562582561809594,
                    -0.8310094779426515
                ],
                [
                    -0.5326856685054707,
                    -0.8463131681410138
                ],
                [
                    -0.5291440014407093,
                    -0.848532041669208
                ],
                [
                    0.13012840712500304,
                    -0.9914971495970674
                ],
                [
                    0.1414710651976511,
                    -0.9899423911076048
                ],
                [
                    0.15412983443904357,
                    -0.9880506030238497
                ],
                [
                    0.5077364310049065,
                    -0.8615124587783972
                ],
                [
                    0.5793403614098387,
                    -0.8150857290135298
                ],
                [
                    0.6068859052829692,
                    -0.79478896442318
                ],
                [
                    0.8621246737891429,
                    -0.5066962076471107
                ],
                [
                    0.9934624250825332,
                    0.11415958106585775
                ],
                [
                    0.9908212100946633,
                    0.1351788801053892
                ],
                [
                    0.9907638009573232,
                    0.13559900704871514
                ],
                [
                    0.9781054245867845,
                    0.208110015121584
                ],
                [
                    0.9025890902252486,
                    0.43050311753384307
                ],
                [
                    0.3997341343274719,
                    0.9166311263826178
                ],
                [
                    0.39120889784374974,
                    0.9203019060329488
                ],
                [
                    -0.11303971441206233,
                    0.9935904704482825
                ],
                [
                    -0.13645931700347272,
                    0.9906456757100117
                ],
                [
                    -0.3456398763374392,
                    0.938367239350053
                ],
                [
                    -0.5005986012751109,
                    0.8656795252294018
                ],
                [
                    -0.5672763570989436,
                    0.8235274947908853
                ],
                [
                    -0.5877237095312687,
                    0.8090617042320103
                ],
                [
                    -0.9881210438862493,
                    0.15367759312648355
                ]
            ]
        },
        {
            "Type": "F",
            "Centroid": {
                "x": 94670.216325,
                "y": 432710.9005
            },
            "Distances": [
                7.91240640104856,
                1.9492566033264613,
                6.100594528818199,
                6.179877940169048,
                6.173377038178562,
                6.070543283382695,
                6.7136456977977526,
                6.702789494316427,
                8.36987370904596,
                8.214299632649613,
                8.462175985232225,
                8.329283192732388,
                3.0101667238308023,
                3.5035231846769803,
                4.018208936233502,
                5.04305064968337,
                4.976403315153955,
                5.48907643006444,
                3.666491914022813,
                2.4645893685407376,
                5.810317453085105,
                5.3186767579674825,
                6.085002071140347,
                5.412318593325902,
                5.22093681782047,
                5.663994280163012,
                8.90848390895349,
                4.69601987918541,
                8.16614431087958,
                7.697283313381356,
                9.698346864619575,
                9.36561845564534,
                11.498334375319297,
                8.081237801592218,
                9.40111434648898,
                9.939089347452652,
                2.5325018668818786,
                7.3830846910870225,
                5.487535959390881,
                3.1112718710644645
            ],
            "UnitPairs": [
                [
                    -0.9487726766671774,
                    -0.31595950374976817
                ],
                [
                    -0.8629315386869807,
                    -0.5053208481146607
                ],
                [
                    -0.6530633991785869,
                    -0.757303239563459
                ],
                [
                    -0.6487304504730744,
                    -0.7610182669483052
                ],
                [
                    -0.6426101913869541,
                    -0.7661932797444925
                ],
                [
                    -0.6268096317528061,
                    -0.7791724363335188
                ],
                [
                    -0.6251558674566974,
                    -0.7804999304192565
                ],
                [
                    -0.6146806495254682,
                    -0.7887760766522706
                ],
                [
                    0.10680268676342604,
                    -0.9942802351953466
                ],
                [
                    0.11892979848365624,
                    -0.9929026654373714
                ],
                [
                    0.12100020157796658,
                    -0.9926524826030969
                ],
                [
                    0.13325576454951982,
                    -0.9910816824128691
                ],
                [
                    0.312914561354656,
                    -0.9497812786595782
                ],
                [
                    0.40585574150652415,
                    -0.913937151606274
                ],
                [
                    0.5407695404780201,
                    -0.8411707936508441
                ],
                [
                    0.5950614436499252,
                    -0.8036802089645276
                ],
                [
                    0.61629349668115,
                    -0.7875165559837592
                ],
                [
                    0.6436283125230179,
                    -0.7653382228262042
                ],
                [
                    0.9292056494036929,
                    -0.36956306784669557
                ],
                [
                    0.9555039999976525,
                    -0.2949781449336313
                ],
                [
                    0.9730836646437221,
                    0.23045212431987733
                ],
                [
                    0.9620673022344427,
                    0.27281221741582856
                ],
                [
                    0.9616964680668912,
                    0.27411658707138975
                ],
                [
                    0.9576163913174297,
                    0.2880466057432083
                ],
                [
                    0.9547951208645394,
                    0.2972646584666089
                ],
                [
                    0.9343097358928503,
                    0.35646222438826847
                ],
                [
                    0.8556927394056209,
                    0.5174842371787806
                ],
                [
                    0.7414630026234119,
                    0.670993752385724
                ],
                [
                    0.329889467714956,
                    0.9440195649936198
                ],
                [
                    0.31750487808483485,
                    0.9482566384646797
                ],
                [
                    -0.1346698585059992,
                    0.9908905233223165
                ],
                [
                    -0.15664475410307158,
                    0.987655011130905
                ],
                [
                    -0.34579573616620113,
                    0.93830981495947
                ],
                [
                    -0.4845885118279072,
                    0.8747422330060519
                ],
                [
                    -0.5481344881119573,
                    0.8363902097360075
                ],
                [
                    -0.5681682498857997,
                    0.8229124132140111
                ],
                [
                    -0.7178968054390235,
                    0.6961495361920775
                ],
                [
                    -0.9666792809002988,
                    0.25599056208790455
                ],
                [
                    -0.98879989856104,
                    0.14924731356268042
                ],
                [
                    -0.9999367232872481,
                    0.011249418721039536
                ]
            ]
        },
        {
            "Type": "R",
            "Centroid": {
                "x": 94668.39825,
                "y": 432712.6635
            },
            "Distances": [
                0.0
            ],
            "UnitPairs": [
                [
                    0.0,
                    0.0
                ]
            ]
        }
    ],
    "Annual Heating [kWh/m2]": 633.9096058715386,
    "Annual Cooling [kWh/m2]": 2.6789650293164353
}