{
    "Pand ID": "0599100000334066",
    "Archetype ID": "D.1975-1991",
    "Construction Year": 1988,
    "Number of Floors": 2,
    "Wall Area": 216.87,
    "Roof Area (Flat)": 5.05,
    "Roof Area (Sloped)": 161.25,
    "Floor Area": 111.83,
    "Shared Wall Area": 0.0,
    "Absolute Height (70%)": 3.255530834197998,
    "Surfaces": [
        {
            "Type": "G",
            "Centroid": {
                "x": 97331.71304166668,
                "y": 437714.74839814816
            },
            "Distances": [
                3.333688801011386,
                3.423799403484108,
                8.243819351709954,
                7.278901533915357,
                6.639361938309869,
                5.176672331647334,
                5.498602262131986,
                6.477451292328924,
                5.361960492039157,
                6.580624015195272,
                8.304743694823285,
                8.683703612459542,
                8.62657875746722,
                8.666315051819852,
                7.09812145099236,
                5.992990707007538,
                5.873460153096409,
                5.752559429081879,
                5.801495134865376,
                1.8885917013764608,
                2.050913361041234,
                0.8769303066337246,
                0.8893061505199731,
                1.5551024331255479,
                3.3600659417750993,
                3.8119638886836453,
                5.117084067645637
            ],
            "UnitPairs": [
                [
                    -0.9999933604064718,
                    -0.00364405584099624
                ],
                [
                    -0.9999612311356011,
                    -0.00880546567609928
                ],
                [
                    -0.6141166431102499,
                    -0.7892152739620527
                ],
                [
                    -0.45112118241604887,
                    -0.8924627044171347
                ],
                [
                    -0.2142776188282594,
                    -0.9767727996158018
                ],
                [
                    -0.014230506000482005,
                    -0.9998987412228151
                ],
                [
                    -0.01285175091735253,
                    -0.9999174128388596
                ],
                [
                    -0.009674587094718572,
                    -0.9999532000871574
                ],
                [
                    0.2650771738139616,
                    -0.9642271993274214
                ],
                [
                    0.6209644136923387,
                    -0.7838387569696524
                ],
                [
                    0.7847723629791074,
                    -0.6197841062048848
                ],
                [
                    0.7447667057699323,
                    0.667324923838907
                ],
                [
                    0.7408885391326945,
                    0.67162800163619
                ],
                [
                    0.7374914591860928,
                    0.675356459677086
                ],
                [
                    0.5682254609438513,
                    0.8228729097103317
                ],
                [
                    0.23382871788691756,
                    0.9722778053063642
                ],
                [
                    -0.14091636703153876,
                    0.9900215035556715
                ],
                [
                    -0.1437041506248198,
                    0.9896206935453599
                ],
                [
                    -0.19696072134914297,
                    0.9804113801081795
                ],
                [
                    -0.40965268782620157,
                    0.9122415663390748
                ],
                [
                    -0.5425225110937398,
                    0.8400412638415703
                ],
                [
                    -0.882244188417895,
                    0.4707920899960511
                ],
                [
                    -0.8857092309663634,
                    0.4642404098966106
                ],
                [
                    -0.9649953821099355,
                    0.26226687268219684
                ],
                [
                    -0.9930360666990462,
                    0.11781073904736941
                ],
                [
                    -0.994675389745327,
                    0.10305760056871974
                ],
                [
                    -0.997182496753617,
                    0.07501378652102869
                ]
            ]
        },
        {
            "Type": "F",
            "Centroid": {
                "x": 97332.11155448717,
                "y": 437714.5531217949
            },
            "Distances": [
                3.130496441717131,
                8.345752464728472,
                6.828859549052457,
                5.780122682785727,
                7.2979059428763335,
                6.548219751994396,
                5.6873336952820335,
                5.003202704763836,
                5.323587011064768,
                6.298777640695088,
                5.078928152361588,
                4.2277961340914425,
                6.183050750824221,
                7.871530901999809,
                3.9329518173410913,
                5.629917178202419,
                5.846187278018466,
                4.43875064398924,
                8.527145966299944,
                8.567280814910623,
                8.472517592566026,
                8.514326308325588,
                7.046045974109876,
                6.105053406784668,
                6.133934885269286,
                6.014242972810295,
                6.203864872505687,
                6.081647119798825,
                2.247936956721943,
                2.441900746073733,
                1.3205395351901994,
                1.3329822540569005,
                1.9926480763759737,
                3.78166608206343,
                4.23125264198465,
                5.531578909138118,
                3.736669595234381,
                3.8257448106524246,
                3.731680187648843
            ],
            "UnitPairs": [
                [
                    -0.972746509653291,
                    -0.23187114515898688
                ],
                [
                    -0.6543663390754612,
                    -0.756177686979045
                ],
                [
                    -0.5399407413030048,
                    -0.8417030330711429
                ],
                [
                    -0.5200892181969751,
                    -0.8541119394524697
                ],
                [
                    -0.5045528835239508,
                    -0.8633807895289694
                ],
                [
                    -0.2781182605578075,
                    -0.9605468406820666
                ],
                [
                    -0.20047698064725725,
                    -0.9796984128958051
                ],
                [
                    -0.09437544609643554,
                    -0.9955366769607732
                ],
                [
                    -0.08813220976501226,
                    -0.9961087860278796
                ],
                [
                    -0.07321729920973752,
                    -0.9973160116514884
                ],
                [
                    0.20138511161283643,
                    -0.979512142252808
                ],
                [
                    0.5496529253363601,
                    -0.8353931180403522
                ],
                [
                    0.596440278666468,
                    -0.8026574574401374
                ],
                [
                    0.7773355131303425,
                    -0.6290862421213702
                ],
                [
                    0.9783543484739052,
                    -0.20693662996724485
                ],
                [
                    0.9889702346585716,
                    -0.1481143982176276
                ],
                [
                    0.8990167887011733,
                    0.43791416240335285
                ],
                [
                    0.8670954558012285,
                    0.4981420184333577
                ],
                [
                    0.7117059490741148,
                    0.7024775028799952
                ],
                [
                    0.7082551213069431,
                    0.7059565731278994
                ],
                [
                    0.7073246467019806,
                    0.7068888485242346
                ],
                [
                    0.7038514024272364,
                    0.7103472413553897
                ],
                [
                    0.5158667039906469,
                    0.8566688646809958
                ],
                [
                    0.16426072730475813,
                    0.9864169572068963
                ],
                [
                    -0.19990096245046204,
                    0.9798161078546213
                ],
                [
                    -0.2037130014049731,
                    0.979030649703357
                ],
                [
                    -0.2485836682226994,
                    0.9686104273096314
                ],
                [
                    -0.2534148162171816,
                    0.9673577057746592
                ],
                [
                    -0.5214467797528458,
                    0.8532838073498098
                ],
                [
                    -0.6188537718384011,
                    0.7855062119941408
                ],
                [
                    -0.8876519452340658,
                    0.4605149553729816
                ],
                [
                    -0.8898689262783026,
                    0.4562162798983621
                ],
                [
                    -0.953093278078012,
                    0.30267673065914596
                ],
                [
                    -0.9877073771480769,
                    0.15631422560748137
                ],
                [
                    -0.9902929089105574,
                    0.1389962393788633
                ],
                [
                    -0.9945043860949132,
                    0.10469491887374431
                ],
                [
                    -0.9987983663119784,
                    0.04900840185644711
                ],
                [
                    -0.9990680707510212,
                    0.04316236793588297
                ],
                [
                    -0.9998658243847903,
                    0.01638087993129912
                ]
            ]
        },
        {
            "Type": "R",
            "Centroid": {
                "x": 97334.398375,
                "y": 437719.24225
            },
            "Distances": [
                0.0
            ],
            "UnitPairs": [
                [
                    0.0,
                    0.0
                ]
            ]
        }
    ],
    "Annual Heating [kWh/m2]": 307.93569455061436,
    "Annual Cooling [kWh/m2]": 1.216166200508771
}