{
    "Pand ID": "0599100000013581",
    "Archetype ID": "D.1965",
    "Construction Year": 1964,
    "Number of Floors": 2,
    "Wall Area": 356.56,
    "Roof Area (Flat)": 68.62,
    "Roof Area (Sloped)": 159.78,
    "Floor Area": 194.41,
    "Shared Wall Area": 0.0,
    "Absolute Height (70%)": 0.9897223711013794,
    "Surfaces": [
        {
            "Type": "G",
            "Centroid": {
                "x": 94431.74467261905,
                "y": 442225.02805952384
            },
            "Distances": [
                5.8395736219659815,
                9.119039312948642,
                8.083921796391257,
                8.13446386504306,
                10.140922473338223,
                10.092716357206923,
                10.198884565108566,
                8.156647875343165,
                8.286889314731729,
                11.567093598838289,
                9.340544711882663,
                4.7249107212887065,
                4.162637263909005,
                10.978718844527863,
                12.034505940352286,
                11.371874638799184,
                11.290268215225378,
                11.533532403614311,
                11.45199582690198,
                11.753533737744695,
                12.431624235546447
            ],
            "UnitPairs": [
                [
                    -0.19557037773414057,
                    -0.9806896692394214
                ],
                [
                    0.2737078211087358,
                    -0.9618128865137482
                ],
                [
                    0.48626798724160886,
                    -0.8738097301953066
                ],
                [
                    0.4882869291504513,
                    -0.8726831468642111
                ],
                [
                    0.5514244286596692,
                    -0.8342248494724651
                ],
                [
                    0.5643626729767203,
                    -0.825526967064415
                ],
                [
                    0.5673122726322457,
                    -0.8235027536813927
                ],
                [
                    0.9838542135925472,
                    -0.17897174748040742
                ],
                [
                    0.988302373772661,
                    -0.15250710801573644
                ],
                [
                    0.9896135345617547,
                    -0.14375344243596588
                ],
                [
                    0.999936584968914,
                    0.01126170682915212
                ],
                [
                    0.9462511875195612,
                    0.323432667054242
                ],
                [
                    0.8052472911858113,
                    0.5929391200097303
                ],
                [
                    -0.4746498833654623,
                    0.8801746918772164
                ],
                [
                    -0.504719317033891,
                    0.8632835055836772
                ],
                [
                    -0.7059563945299117,
                    0.7082552993252699
                ],
                [
                    -0.794228042072453,
                    0.6076197965716372
                ],
                [
                    -0.8783993718941474,
                    0.4779273411889796
                ],
                [
                    -0.8790649046001688,
                    0.47670210142215236
                ],
                [
                    -0.9105387245951297,
                    0.413423791057886
                ],
                [
                    -0.9632729715890219,
                    0.26852408124050137
                ]
            ]
        },
        {
            "Type": "F",
            "Centroid": {
                "x": 94430.81188214285,
                "y": 442225.0821357143
            },
            "Distances": [
                6.331746095821287,
                4.256270479348532,
                3.81687253714691,
                2.791854293017384,
                5.7846718310904235,
                9.46757019781278,
                8.620921738541792,
                8.672962385249752,
                10.726533424542882,
                10.833216332557486,
                10.689401811089091,
                10.797813782406495,
                3.4269988651808987,
                3.372822941331632,
                3.0634111648400455,
                9.084767858935685,
                9.767502126623302,
                9.21744324601472,
                12.49822906515816,
                10.272870021536404,
                2.475268313159354,
                5.601200745691581,
                4.918024922312512,
                10.518486656200276,
                11.54327130008588,
                10.307437174575965,
                9.523728807210636,
                10.693198890322899,
                10.52960015896478,
                10.695744294906449,
                10.61366637846338,
                10.887033958889937,
                9.6212124254885,
                11.520279920665912,
                8.907206929175421
            ],
            "UnitPairs": [
                [
                    -0.9962902882376031,
                    -0.08605615354774904
                ],
                [
                    -0.9710983272573498,
                    -0.23867978296868178
                ],
                [
                    -0.9340781249970441,
                    -0.35706869983520895
                ],
                [
                    -0.8894651662398042,
                    -0.4570029737824443
                ],
                [
                    -0.036174419044214604,
                    -0.9993454915127268
                ],
                [
                    0.3621565814159238,
                    -0.9321172729528895
                ],
                [
                    0.5641789827888543,
                    -0.8256525149112874
                ],
                [
                    0.5655210571986158,
                    -0.8247338563833548
                ],
                [
                    0.6082806624381228,
                    -0.793722014123231
                ],
                [
                    0.610044390721402,
                    -0.7923672389424953
                ],
                [
                    0.6201229006356228,
                    -0.7845046769186668
                ],
                [
                    0.6222317769635917,
                    -0.782833070160383
                ],
                [
                    0.6684399228792715,
                    -0.7437661389853357
                ],
                [
                    0.7773141083176345,
                    -0.6291126902315363
                ],
                [
                    0.7784599352893954,
                    -0.6276942959349163
                ],
                [
                    0.9860178043338121,
                    -0.16663999981015395
                ],
                [
                    0.9866128240593862,
                    -0.1630801502377362
                ],
                [
                    0.9897259591034729,
                    -0.14297736141330356
                ],
                [
                    0.9905197602488836,
                    -0.13737031905216723
                ],
                [
                    0.9999876213381793,
                    0.004975657786658961
                ],
                [
                    0.9888798091675035,
                    0.1487169224427469
                ],
                [
                    0.9647472216208215,
                    0.26317826349245815
                ],
                [
                    0.8712324408352509,
                    0.49087068973024967
                ],
                [
                    -0.4067369463583805,
                    0.9135453226124362
                ],
                [
                    -0.44538996002056863,
                    0.895336687237196
                ],
                [
                    -0.5457474101053625,
                    0.8379497385662754
                ],
                [
                    -0.625307299630524,
                    0.7803786138976273
                ],
                [
                    -0.6635298955554617,
                    0.7481497695676703
                ],
                [
                    -0.763016355944717,
                    0.6463791770786285
                ],
                [
                    -0.8599922445072794,
                    0.5103071030147746
                ],
                [
                    -0.8606128002467395,
                    0.5092598629888926
                ],
                [
                    -0.8973295371115838,
                    0.4413611920265654
                ],
                [
                    -0.9110345718619706,
                    0.4123299757139613
                ],
                [
                    -0.9585059754530312,
                    0.28507243819919353
                ],
                [
                    -0.9815935806108168,
                    0.19098178579025732
                ]
            ]
        },
        {
            "Type": "R",
            "Centroid": {
                "x": 94433.315125,
                "y": 442223.05975
            },
            "Distances": [
                0.15473364212390225,
                0.15473364211275795
            ],
            "UnitPairs": [
                [
                    0.7658321641296362,
                    -0.6430405091318261
                ],
                [
                    -0.7658321640907484,
                    0.6430405091781395
                ]
            ]
        }
    ],
    "Annual Heating [kWh/m2]": 354.27561297418725,
    "Annual Cooling [kWh/m2]": 1.3997495473611052
}