{
    "Pand ID": "0599100000089769",
    "Archetype ID": "D.1965",
    "Construction Year": 1924,
    "Number of Floors": 2,
    "Wall Area": 187.61,
    "Roof Area (Flat)": 20.73,
    "Roof Area (Sloped)": 89.44,
    "Floor Area": 76.53,
    "Shared Wall Area": 0.0,
    "Absolute Height (70%)": 6.235653400421143,
    "Surfaces": [
        {
            "Type": "G",
            "Centroid": {
                "x": 97487.15226086955,
                "y": 434863.6405652174
            },
            "Distances": [
                5.264297227600211,
                6.149853741324243,
                5.8361656631975585,
                6.084340819975408,
                3.8419665815307305,
                3.7012928171440187,
                5.140374546140402,
                5.0596213680013475,
                4.852498289396395,
                4.965860334931177,
                6.783711466239531,
                4.040877454837298,
                3.971010630940792,
                7.82250729547483,
                5.723276626559599,
                5.592575621576629,
                5.707226345734368,
                6.418213417613317,
                6.567858035138592,
                5.287861982297855,
                5.139489523412247,
                5.218700974935274,
                5.913255168841079
            ],
            "UnitPairs": [
                [
                    -0.9999930934675403,
                    -0.003716586770061812
                ],
                [
                    -0.9914481101539712,
                    -0.13050151291122664
                ],
                [
                    -0.958208041423325,
                    -0.2860722799428066
                ],
                [
                    -0.9309571960463588,
                    -0.36512833241136095
                ],
                [
                    0.304463640072007,
                    -0.9525239586877086
                ],
                [
                    0.35899324805995225,
                    -0.9333401565599573
                ],
                [
                    0.6146904475688443,
                    -0.7887684410951123
                ],
                [
                    0.6294421852568991,
                    -0.777047318648626
                ],
                [
                    0.6319918004188583,
                    -0.7749750732787023
                ],
                [
                    0.6469652615558202,
                    -0.7625194753840777
                ],
                [
                    0.9974980752230029,
                    -0.07069363427073357
                ],
                [
                    0.9999657687242914,
                    0.008274139208215535
                ],
                [
                    0.9999316293694545,
                    0.011693442031670572
                ],
                [
                    0.9426311605629721,
                    0.3338360303138415
                ],
                [
                    0.8386348316913691,
                    0.5446940600685755
                ],
                [
                    0.8258697678796892,
                    0.5638609105997224
                ],
                [
                    0.8147108330334636,
                    0.5798674491105014
                ],
                [
                    -0.6212415527686479,
                    0.7836191250305209
                ],
                [
                    -0.6361679633163189,
                    0.7715505961697955
                ],
                [
                    -0.8958745302766162,
                    0.4443071302619983
                ],
                [
                    -0.9538419812358174,
                    0.30030896562062614
                ],
                [
                    -0.9594841501001781,
                    0.2817626052309617
                ],
                [
                    -0.9998318524651633,
                    0.018337578795463483
                ]
            ]
        },
        {
            "Type": "F",
            "Centroid": {
                "x": 97486.98347058822,
                "y": 434863.95964705886
            },
            "Distances": [
                5.747332127283272,
                5.106711500175441,
                6.033643645442695,
                2.9093267755928025,
                2.8836945653141846,
                5.776569080863229,
                6.054344263731369,
                6.098709014231439,
                4.197772433675227,
                4.05992690378331,
                5.4961710890736395,
                5.414255252050556,
                5.206934866047901,
                5.318935883672771,
                2.3015209789773134,
                6.981361281735873,
                4.219209891773139,
                4.148498544001226,
                4.712201751411301,
                7.883186661141838,
                5.84970742295577,
                5.402718764826661,
                5.702373514507182,
                2.472164708500216,
                5.563631409743301,
                5.671017228396963,
                6.0636740069983315,
                6.214717214116072,
                5.50595457279864,
                3.0407496548513553,
                4.999325612629197,
                4.8892518787728685,
                4.973571275086191,
                5.608347742851397
            ],
            "UnitPairs": [
                [
                    -0.999328116252127,
                    -0.03665127648493798
                ],
                [
                    -0.9977987963598921,
                    -0.06631411601424297
                ],
                [
                    -0.9825688981000493,
                    -0.1858987909763132
                ],
                [
                    -0.9636148856670665,
                    -0.2672945044718399
                ],
                [
                    -0.9576154914065405,
                    -0.28804959749704584
                ],
                [
                    -0.9388740119447985,
                    -0.3442609325710344
                ],
                [
                    -0.9076904696594715,
                    -0.4196403356320361
                ],
                [
                    -0.9028911816214901,
                    -0.4298691826011136
                ],
                [
                    0.3188665972071765,
                    -0.947799606027306
                ],
                [
                    0.368856249697565,
                    -0.9294864534026559
                ],
                [
                    0.6056087697822752,
                    -0.7957625386777133
                ],
                [
                    0.6193888643328063,
                    -0.7850843488062391
                ],
                [
                    0.621388493424559,
                    -0.783502610231489
                ],
                [
                    0.6357529937795947,
                    -0.7718925643509483
                ],
                [
                    0.6841255961375706,
                    -0.7293642222575862
                ],
                [
                    0.9934351098423496,
                    -0.11439703900240948
                ],
                [
                    0.9977056178179896,
                    -0.06770155223053462
                ],
                [
                    0.9978379811062275,
                    -0.06572186441244576
                ],
                [
                    0.9973107391589239,
                    0.0732890821219711
                ],
                [
                    0.95678685993229,
                    0.2907901385207357
                ],
                [
                    0.9177432345945099,
                    0.39717421285376303
                ],
                [
                    0.8874290186972132,
                    0.4609443966186171
                ],
                [
                    0.8713090082797933,
                    0.49073476755828405
                ],
                [
                    0.8698973027050325,
                    0.4932328889546085
                ],
                [
                    0.8605044186401714,
                    0.509442975710472
                ],
                [
                    0.8496763839199438,
                    0.527304506531784
                ],
                [
                    -0.6297288712789243,
                    0.7768150028660441
                ],
                [
                    -0.6451573659907637,
                    0.7640497190025397
                ],
                [
                    -0.6522884525736178,
                    0.7579708270369747
                ],
                [
                    -0.7348420099835811,
                    0.6782383212140779
                ],
                [
                    -0.9138173710249302,
                    0.40612536538990646
                ],
                [
                    -0.9681380108017755,
                    0.25041723590995285
                ],
                [
                    -0.9728362821442901,
                    0.23149420758125935
                ],
                [
                    -0.9936029011992168,
                    0.11293039771691032
                ]
            ]
        },
        {
            "Type": "R",
            "Centroid": {
                "x": 97484.18,
                "y": 434863.18200000003
            },
            "Distances": [
                0.0
            ],
            "UnitPairs": [
                [
                    0.0,
                    0.0
                ]
            ]
        }
    ],
    "Annual Heating [kWh/m2]": 423.74979633616397,
    "Annual Cooling [kWh/m2]": 1.84907894014358
}