{
    "Pand ID": "0599100000131194",
    "Archetype ID": "D.1975-1991",
    "Construction Year": 1984,
    "Number of Floors": 2,
    "Wall Area": 290.7,
    "Roof Area (Flat)": 99.43,
    "Roof Area (Sloped)": 52.55,
    "Floor Area": 134.67,
    "Shared Wall Area": 0.0,
    "Absolute Height (70%)": 4.7300705909729,
    "Surfaces": [
        {
            "Type": "G",
            "Centroid": {
                "x": 95723.61189423077,
                "y": 437806.32711538457
            },
            "Distances": [
                7.939989036080159,
                7.6673544811344225,
                7.808301630618251,
                11.652104523049875,
                10.472280662692048,
                10.87269476757268,
                6.329770208603195,
                5.921201922021804,
                3.111020233565261,
                6.833280891326861,
                6.776030677326552,
                6.913457292821774,
                6.324710237309789
            ],
            "UnitPairs": [
                [
                    -0.9676045137902293,
                    -0.2524708000794823
                ],
                [
                    -0.9602750530029366,
                    -0.27905523213193373
                ],
                [
                    -0.9535709022261265,
                    -0.301168614612564
                ],
                [
                    0.659042386209871,
                    -0.7521057991923737
                ],
                [
                    0.9171097565648729,
                    -0.39863478826304116
                ],
                [
                    0.9922315488345879,
                    -0.12440479692244528
                ],
                [
                    0.9962811541995793,
                    0.08616183486181157
                ],
                [
                    0.9924050634691559,
                    0.12301296679936008
                ],
                [
                    0.6529146764528628,
                    0.757431465726407
                ],
                [
                    -0.660703006735153,
                    0.7506474118326981
                ],
                [
                    -0.6730738758332326,
                    0.7395752549070513
                ],
                [
                    -0.6799447847364707,
                    0.7332633153988235
                ],
                [
                    -0.9514695543304684,
                    0.30774289135929633
                ]
            ]
        },
        {
            "Type": "F",
            "Centroid": {
                "x": 95723.92367045455,
                "y": 437806.3432272727
            },
            "Distances": [
                8.245974517010069,
                8.384463294412448,
                7.971562457138018,
                8.110834970402276,
                11.46136978995814,
                7.288518617962089,
                8.383987785651462,
                10.193718975607743,
                10.565486935767833,
                4.439629264745163,
                0.2199181853907446,
                6.017774914161692,
                5.609856221558336,
                2.9040317443268266,
                2.7983666842212678,
                1.2023699359346498,
                7.031436482574744,
                7.166489898362068,
                6.978140785836372,
                7.117666555142376,
                6.617333183618647,
                3.53625617504991
            ],
            "UnitPairs": [
                [
                    -0.9695088722438222,
                    -0.24505621118533608
                ],
                [
                    -0.9639907971124941,
                    -0.2659355995018683
                ],
                [
                    -0.9627404283426566,
                    -0.27042719470237836
                ],
                [
                    -0.9564422754072213,
                    -0.29192151995674664
                ],
                [
                    0.642807507346196,
                    -0.766027746559725
                ],
                [
                    0.8857018667072215,
                    -0.4642544596569248
                ],
                [
                    0.8910383383720902,
                    -0.4539280554791742
                ],
                [
                    0.9115862981601262,
                    -0.41110877028679127
                ],
                [
                    0.991573280923409,
                    -0.12954701292884482
                ],
                [
                    0.9979334492290073,
                    0.06425597956530288
                ],
                [
                    0.9978917617250079,
                    0.0649001685772833
                ],
                [
                    0.9961247522496822,
                    0.08795156596394066
                ],
                [
                    0.9919068021872364,
                    0.12696808959219147
                ],
                [
                    0.5920922003741793,
                    0.8058702291660008
                ],
                [
                    0.5851465266124449,
                    0.810927581472841
                ],
                [
                    0.28564798170761513,
                    0.9583346130378293
                ],
                [
                    -0.6864238148930548,
                    0.7272017232843065
                ],
                [
                    -0.6924652828548565,
                    0.7214511986550051
                ],
                [
                    -0.6982584049356778,
                    0.7158457934057327
                ],
                [
                    -0.7042399943437436,
                    0.7099619921986838
                ],
                [
                    -0.956510013764013,
                    0.2916994918904861
                ],
                [
                    -0.9780245783511805,
                    0.2084896259793173
                ]
            ]
        },
        {
            "Type": "R",
            "Centroid": {
                "x": 95716.047625,
                "y": 437804.149
            },
            "Distances": [
                0.2101059256439263,
                0.21010592569199266
            ],
            "UnitPairs": [
                [
                    0.5640012276364008,
                    -0.8257739492286207
                ],
                [
                    -0.5640012275073731,
                    0.8257739493167463
                ]
            ]
        }
    ],
    "Annual Heating [kWh/m2]": 304.727485706525,
    "Annual Cooling [kWh/m2]": 1.220243401061974
}